[
  {"id":"units-of-time-p1","topicId":"units-of-time","difficulty":"easy","question":"How many seconds are in 1 minute?","answer":"60","hints":["1 minute = 60 seconds."],"solution":"1 minute = 60 seconds.","cognitiveDemand":"procedural"},
  {"id":"units-of-time-p2","topicId":"units-of-time","difficulty":"easy","question":"How many minutes are in 1 hour?","answer":"60","hints":["1 hour = 60 minutes."],"solution":"1 hour = 60 minutes.","cognitiveDemand":"procedural"},
  {"id":"units-of-time-p3","topicId":"units-of-time","difficulty":"easy","question":"How many hours are in 1 day?","answer":"24","hints":["1 day = 24 hours."],"solution":"1 day = 24 hours.","cognitiveDemand":"procedural"},
  {"id":"units-of-time-p4","topicId":"units-of-time","difficulty":"easy","question":"How many days are in 1 week?","answer":"7","hints":["1 week = 7 days."],"solution":"1 week = 7 days.","cognitiveDemand":"procedural"},
  {"id":"units-of-time-p5","topicId":"units-of-time","difficulty":"easy","question":"Which is longer: 1 hour or 1 minute?","answer":"1 hour","hints":["1 hour = 60 minutes."],"solution":"1 hour is 60 times longer than 1 minute.","cognitiveDemand":"conceptual"},
  {"id":"units-of-time-p6","topicId":"units-of-time","difficulty":"medium","question":"How many minutes are in 3 hours?","answer":"180","hints":["3 × 60 = 180."],"solution":"3 × 60 = 180 minutes.","cognitiveDemand":"procedural"},
  {"id":"units-of-time-p7","topicId":"units-of-time","difficulty":"medium","question":"How many seconds are in 5 minutes?","answer":"300","hints":["5 × 60 = 300."],"solution":"5 × 60 = 300 seconds.","cognitiveDemand":"procedural"},
  {"id":"units-of-time-p8","topicId":"units-of-time","difficulty":"medium","question":"How many hours are in 3 days?","answer":"72","hints":["3 × 24 = 72."],"solution":"3 × 24 = 72 hours.","cognitiveDemand":"procedural"},
  {"id":"units-of-time-p9","topicId":"units-of-time","difficulty":"medium","question":"Which is longer: 200 minutes or 3 hours?","answer":"200 minutes","hints":["3 hours = 180 minutes. 200 > 180."],"solution":"3 hours = 180 minutes. 200 > 180, so 200 minutes is longer.","cognitiveDemand":"conceptual"},
  {"id":"units-of-time-p10","topicId":"units-of-time","difficulty":"medium","question":"A movie is 2 hours and 15 minutes long. How many minutes is that total?","answer":"135 minutes","hints":["2 × 60 + 15 = 135."],"solution":"2 × 60 + 15 = 120 + 15 = 135 minutes.","cognitiveDemand":"procedural"},
  {"id":"units-of-time-p11","topicId":"units-of-time","difficulty":"hard","question":"How many seconds are in 1 hour?","answer":"3,600","hints":["60 minutes × 60 seconds = 3,600."],"solution":"1 hour = 60 min × 60 sec = 3,600 seconds.","cognitiveDemand":"procedural"},
  {"id":"units-of-time-p12","topicId":"units-of-time","difficulty":"hard","question":"A race took 150 seconds. Express this in minutes and seconds.","answer":"2 minutes 30 seconds","hints":["150 ÷ 60 = 2 remainder 30."],"solution":"150 ÷ 60 = 2 min 30 sec.","cognitiveDemand":"procedural"},
  {"id":"units-of-time-p13","topicId":"units-of-time","difficulty":"hard","question":"How many minutes are in 1 day?","answer":"1,440","hints":["24 hours × 60 minutes = 1,440."],"solution":"24 × 60 = 1,440 minutes.","cognitiveDemand":"procedural"},
  {"id":"units-of-time-p14","topicId":"units-of-time","difficulty":"hard","question":"You sleep 9 hours per night. How many hours do you sleep in 2 weeks?","answer":"126 hours","hints":["2 weeks = 14 days. 14 × 9 = 126."],"solution":"2 weeks = 14 days. 14 × 9 = 126 hours.","cognitiveDemand":"problem-solving"},
  {"id":"units-of-time-p15","topicId":"units-of-time","difficulty":"hard","question":"Order from shortest to longest: 2 days, 50 hours, 3,000 minutes.","answer":"2 days, 50 hours, 3,000 minutes","hints":["Convert to hours: 2 days = 48 hr. 50 hr. 3,000 min = 50 hr. Wait: 3000/60 = 50 exactly."],"solution":"2 days = 48 hr. 50 hr = 50 hr. 3,000 min = 50 hr. So: 2 days (48 hr) < 50 hours = 3,000 minutes (tied).","cognitiveDemand":"conceptual"}
]
