[
  {
    "id": "place-value-hundreds-sup-e0",
    "topicId": "place-value-hundreds",
    "difficulty": "easy",
    "question": "In the number 453, what digit is in the hundreds place?",
    "answer": "4",
    "hints": [
      "The hundreds place is the leftmost digit in a three-digit number."
    ],
    "solution": "In 453, the digit 4 is in the hundreds place. It represents 400.",
    "cognitiveDemand": "conceptual",
    "source": "generated"
  },
  {
    "id": "place-value-hundreds-sup-e1",
    "topicId": "place-value-hundreds",
    "difficulty": "easy",
    "question": "What number has 3 hundreds, 2 tens, and 5 ones?",
    "answer": "325",
    "hints": [
      "3 hundreds = 300, 2 tens = 20, 5 ones = 5."
    ],
    "solution": "3 hundreds + 2 tens + 5 ones = 300 + 20 + 5 = 325.",
    "cognitiveDemand": "conceptual",
    "source": "generated"
  },
  {
    "id": "place-value-hundreds-sup-e2",
    "topicId": "place-value-hundreds",
    "difficulty": "easy",
    "question": "How many hundreds are in 700?",
    "answer": "7",
    "hints": [
      "700 = ? hundreds + 0 tens + 0 ones."
    ],
    "solution": "700 has 7 hundreds, 0 tens, and 0 ones.",
    "cognitiveDemand": "conceptual",
    "source": "generated"
  },
  {
    "id": "place-value-hundreds-sup-e3",
    "topicId": "place-value-hundreds",
    "difficulty": "easy",
    "question": "What is the value of the digit 6 in 621?",
    "answer": "600",
    "hints": [
      "The 6 is in the hundreds place."
    ],
    "solution": "In 621, the 6 is in the hundreds place. Its value is 6 hundreds = 600.",
    "cognitiveDemand": "conceptual",
    "source": "generated"
  },
  {
    "id": "place-value-hundreds-sup-e4",
    "topicId": "place-value-hundreds",
    "difficulty": "easy",
    "question": "Write 500 + 30 + 8 as a single number.",
    "answer": "538",
    "hints": [
      "5 hundreds, 3 tens, 8 ones."
    ],
    "solution": "500 + 30 + 8 = 538.",
    "cognitiveDemand": "conceptual",
    "source": "generated"
  },
  {
    "id": "place-value-hundreds-sup-m0",
    "topicId": "place-value-hundreds",
    "difficulty": "medium",
    "question": "Write 849 in expanded form.",
    "answer": "800 + 40 + 9",
    "hints": [
      "Break each digit into its place value.",
      "8 hundreds + 4 tens + 9 ones."
    ],
    "solution": "849 = 800 + 40 + 9. The 8 is worth 800, the 4 is worth 40, and the 9 is worth 9.",
    "cognitiveDemand": "conceptual",
    "source": "generated"
  },
  {
    "id": "place-value-hundreds-sup-m1",
    "topicId": "place-value-hundreds",
    "difficulty": "medium",
    "question": "Which is greater: 382 or 328?",
    "answer": "382",
    "hints": [
      "Both start with 3 hundreds. Compare the tens next.",
      "8 tens vs. 2 tens."
    ],
    "solution": "Both have 3 hundreds. Compare tens: 382 has 8 tens, 328 has 2 tens. 8 > 2, so 382 > 328.",
    "cognitiveDemand": "reasoning",
    "source": "generated"
  },
  {
    "id": "place-value-hundreds-sup-m2",
    "topicId": "place-value-hundreds",
    "difficulty": "medium",
    "question": "What is 100 more than 456?",
    "answer": "556",
    "hints": [
      "Adding 100 increases the hundreds digit by 1."
    ],
    "solution": "456 + 100 = 556. The hundreds digit goes from 4 to 5. The tens and ones stay the same.",
    "cognitiveDemand": "application",
    "source": "generated"
  },
  {
    "id": "place-value-hundreds-sup-m3",
    "topicId": "place-value-hundreds",
    "difficulty": "medium",
    "question": "In the number 909, what is the value of each 9?",
    "answer": "900 and 9",
    "hints": [
      "The first 9 is in the hundreds place. The second 9 is in the ones place.",
      "Same digit, different values because of different positions."
    ],
    "solution": "In 909, the first 9 is in the hundreds place (value = 900) and the second 9 is in the ones place (value = 9). Same digit, but position determines value.",
    "cognitiveDemand": "reasoning",
    "source": "generated"
  },
  {
    "id": "place-value-hundreds-sup-m4",
    "topicId": "place-value-hundreds",
    "difficulty": "medium",
    "question": "How many ones are equal to 1 hundred?",
    "answer": "100",
    "hints": [
      "Think about it: 1 hundred = 10 tens. 1 ten = 10 ones.",
      "So 10 tens = 10 x 10 ones."
    ],
    "solution": "1 hundred = 100 ones. You can also think: 1 hundred = 10 tens, and 10 tens = 10 x 10 = 100 ones.",
    "cognitiveDemand": "conceptual",
    "source": "generated"
  },
  {
    "id": "place-value-hundreds-sup-h0",
    "topicId": "place-value-hundreds",
    "difficulty": "hard",
    "question": "Using the digits 4, 7, and 1 (each used once), what is the largest three-digit number you can make?",
    "answer": "741",
    "hints": [
      "Put the largest digit in the hundreds place.",
      "Then the next largest in the tens, and the smallest in the ones."
    ],
    "solution": "To make the largest number, arrange digits from greatest to least: 7 in hundreds, 4 in tens, 1 in ones = 741.",
    "cognitiveDemand": "reasoning",
    "source": "generated"
  },
  {
    "id": "place-value-hundreds-sup-h1",
    "topicId": "place-value-hundreds",
    "difficulty": "hard",
    "question": "I am a three-digit number. My hundreds digit is 5. My tens digit is double my ones digit. My ones digit is 3. What number am I?",
    "answer": "563",
    "hints": [
      "Ones digit = 3. Tens digit = double 3 = 6.",
      "Put it together: 5 hundreds, 6 tens, 3 ones."
    ],
    "solution": "Hundreds = 5, ones = 3, tens = 2 x 3 = 6. The number is 563.",
    "cognitiveDemand": "reasoning",
    "source": "generated"
  },
  {
    "id": "place-value-hundreds-sup-h2",
    "topicId": "place-value-hundreds",
    "difficulty": "hard",
    "question": "The number 450 can be thought of as 45 tens. Explain why this is true.",
    "answer": "45 tens = 45 x 10 = 450",
    "hints": [
      "Each ten is worth 10.",
      "45 groups of 10 = ?"
    ],
    "solution": "45 tens = 45 x 10 = 450. We can regroup: 4 hundreds + 5 tens = 40 tens + 5 tens = 45 tens.",
    "cognitiveDemand": "reasoning",
    "source": "generated"
  },
  {
    "id": "place-value-hundreds-sup-h3",
    "topicId": "place-value-hundreds",
    "difficulty": "hard",
    "question": "A school has 100 students in each grade. There are 3 grades. Then 47 new students join. How many students are there now?",
    "answer": "347",
    "hints": [
      "3 grades x 100 students each = 300.",
      "300 + 47 = ?"
    ],
    "solution": "3 grades x 100 = 300 students. Plus 47 new students: 300 + 47 = 347 students.",
    "cognitiveDemand": "application",
    "source": "generated"
  },
  {
    "id": "place-value-hundreds-sup-h4",
    "topicId": "place-value-hundreds",
    "difficulty": "hard",
    "question": "What is 10 less than 305?",
    "answer": "295",
    "hints": [
      "Subtracting 10 from 305: the tens digit is 0, so you need to regroup.",
      "Think of 305 as 2 hundreds + 10 tens + 5 ones."
    ],
    "solution": "305 - 10 = 295. Since there are 0 tens in 305, we regroup: 3 hundreds becomes 2 hundreds and 10 tens. Then 10 tens - 1 ten = 9 tens. Result: 295.",
    "cognitiveDemand": "application",
    "source": "generated"
  }
]
