{
  "generatedAt": "2026-03-09T23:18:13.267Z",
  "seed": 42,
  "sessions": 30,
  "profiles": {
    "underconfident": {
      "placementAccuracy": 1,
      "finalMasteryPercent": 0.3380281690140845,
      "sessionsTo50Mastery": null,
      "difficultyConvergencePoint": 561,
      "sameStrandAdjacencyRate": 0.7623497997329773,
      "reviewNewRatio": 0.09358638743455497,
      "demandEntropy": 0.970404206537276,
      "remediationEvents": 1279,
      "fireReviewsSkipped": 0
    },
    "struggling-young": {
      "placementAccuracy": 0,
      "finalMasteryPercent": 0.15492957746478872,
      "sessionsTo50Mastery": null,
      "difficultyConvergencePoint": 145,
      "sameStrandAdjacencyRate": 0.7579787234042553,
      "reviewNewRatio": 0.0752405949256343,
      "demandEntropy": 0.9851908429603894,
      "remediationEvents": 2018,
      "fireReviewsSkipped": 0
    },
    "struggling-older": {
      "placementAccuracy": 1,
      "finalMasteryPercent": 0.22535211267605634,
      "sessionsTo50Mastery": null,
      "difficultyConvergencePoint": 427,
      "sameStrandAdjacencyRate": 0.9316770186335404,
      "reviewNewRatio": 0.07677814413565709,
      "demandEntropy": 0.9884173630209072,
      "remediationEvents": 1858,
      "fireReviewsSkipped": 0
    },
    "strong-young": {
      "placementAccuracy": 1,
      "finalMasteryPercent": 0.4225352112676056,
      "sessionsTo50Mastery": null,
      "difficultyConvergencePoint": 10,
      "sameStrandAdjacencyRate": 0.853429203539823,
      "reviewNewRatio": 0.07181719260065289,
      "demandEntropy": 0.9651634751116239,
      "remediationEvents": 1574,
      "fireReviewsSkipped": 0
    },
    "strong-older": {
      "placementAccuracy": 0,
      "finalMasteryPercent": 1,
      "sessionsTo50Mastery": 0,
      "difficultyConvergencePoint": 127,
      "sameStrandAdjacencyRate": 0.7061503416856492,
      "reviewNewRatio": 0.0881057268722467,
      "demandEntropy": 0.9094868196421737,
      "remediationEvents": 166,
      "fireReviewsSkipped": 0
    },
    "overconfident": {
      "placementAccuracy": 0,
      "finalMasteryPercent": 0.29577464788732394,
      "sessionsTo50Mastery": null,
      "difficultyConvergencePoint": 36,
      "sameStrandAdjacencyRate": 0.7215363511659808,
      "reviewNewRatio": 0.07803337843933243,
      "demandEntropy": 0.8938576659096373,
      "remediationEvents": 1924,
      "fireReviewsSkipped": 0
    },
    "misconception-fractions": {
      "placementAccuracy": 0,
      "finalMasteryPercent": 0.8591549295774648,
      "sessionsTo50Mastery": 0,
      "difficultyConvergencePoint": 120,
      "sameStrandAdjacencyRate": 0.6988082340195017,
      "reviewNewRatio": 0.07569296375266525,
      "demandEntropy": 0.8470740530369704,
      "remediationEvents": 594,
      "fireReviewsSkipped": 0
    },
    "fast-learner": {
      "placementAccuracy": 1,
      "finalMasteryPercent": 0.36619718309859156,
      "sessionsTo50Mastery": null,
      "difficultyConvergencePoint": 86,
      "sameStrandAdjacencyRate": 0.760998810939358,
      "reviewNewRatio": 0.07535046728971963,
      "demandEntropy": 0.9628419909916648,
      "remediationEvents": 1462,
      "fireReviewsSkipped": 0
    },
    "average-young": {
      "placementAccuracy": 1,
      "finalMasteryPercent": 0.2112676056338028,
      "sessionsTo50Mastery": null,
      "difficultyConvergencePoint": 90,
      "sameStrandAdjacencyRate": 0.7179715302491103,
      "reviewNewRatio": 0.07155399473222125,
      "demandEntropy": 1.0047649941816355,
      "remediationEvents": 2008,
      "fireReviewsSkipped": 0
    },
    "average-older": {
      "placementAccuracy": 0,
      "finalMasteryPercent": 0.7605633802816901,
      "sessionsTo50Mastery": 0,
      "difficultyConvergencePoint": 114,
      "sameStrandAdjacencyRate": 0.7553879310344828,
      "reviewNewRatio": 0.06574761399787911,
      "demandEntropy": 0.9596444635193143,
      "remediationEvents": 692,
      "fireReviewsSkipped": 0
    }
  },
  "contentQuality": {
    "tooHard": [
      "line-symmetry",
      "multi-digit-multiply",
      "patterns-arithmetic",
      "perimeter",
      "bar-graphs-picture-graphs",
      "intro-arrays",
      "factors-multiples",
      "angles-intro"
    ],
    "tooEasy": [],
    "perTopicAccuracy": {
      "intro-arrays": 0.6764705882352942,
      "subtract-within-1000": 0.8544061302681992,
      "subtract-within-100-fluent": 0.69,
      "count-to-10": 0.8326055312954876,
      "count-to-20": 0.8652849740932642,
      "count-to-100": 0.7853403141361257,
      "compare-numbers-k": 0.8026315789473685,
      "add-within-5": 0.8785714285714286,
      "subtract-within-5": 0.7843137254901961,
      "add-within-10": 0.8185840707964602,
      "skip-count-2-5-10": 0.6078431372549019,
      "teen-numbers": 0.8181818181818182,
      "shapes-2d-k": 0.9246307558644656,
      "shapes-3d-k": 0.8529411764705882,
      "measure-length-nonstandard": 0.7857142857142857,
      "tell-time-hour-half": 0.7777777777777778,
      "place-value-hundreds": 0.6477916194790487,
      "place-value-tens-ones": 0.7920673076923077,
      "add-within-100-fluent": 0.8490230905861457,
      "measure-length-standard": 0.7438330170777988,
      "money-coins-bills": 0.8181818181818182,
      "tell-time-minute": 0.5,
      "multiply-within-100": 0.7589395807644883,
      "bar-graphs-picture-graphs": 0.4431818181818182,
      "line-symmetry": 0.4036144578313253,
      "odd-even": 0.76,
      "divide-within-100": 0.856687898089172,
      "angles-intro": 0.42452830188679247,
      "intro-fractions": 0.9245283018867925,
      "subtract-within-20": 0.7311178247734139,
      "compare-two-digit": 0.8461538461538461,
      "add-within-20": 0.9285714285714286,
      "subtract-within-10": 0.9032258064516129,
      "add-within-100": 0.7928571428571428,
      "place-value-rounding": 0.5901639344262295,
      "perimeter": 0.6896551724137931,
      "properties-of-multiplication": 0.8387096774193549,
      "multiply-word-problems": 0.675,
      "add-subtract-word-problems-1": 0.8285714285714286,
      "add-within-1000": 0.8205128205128205,
      "patterns-arithmetic": 0.6595744680851063,
      "multi-digit-add-sub": 0.7976190476190477,
      "area-intro": 0.71875,
      "multiply-fractions": 0.4090909090909091,
      "coordinate-plane": 1,
      "add-subtract-fractions-unlike": 0.25,
      "divide-fractions": 0.4090909090909091,
      "order-of-operations": 0.75,
      "divide-multi-digit": 0.7142857142857143,
      "decimal-operations": 0.8,
      "division-word-problems": 0.8181818181818182,
      "place-value-decimals": 0.8,
      "fractions-number-line": 0.8734177215189873,
      "equivalent-fractions-3": 0.7058823529411765,
      "compare-fractions-3": 0.9090909090909091,
      "area-multiply": 0.9245283018867925,
      "multi-digit-multiply": 0.6818181818181818,
      "variables-expressions": 1,
      "long-division": 0.8282828282828283,
      "factors-multiples": 0.6470588235294118,
      "equivalent-fractions-4": 0.8166666666666667,
      "compare-fractions-4": 1,
      "add-subtract-fractions": 0.8461538461538461,
      "multiply-fraction-by-whole": 0.8983050847457628,
      "decimals-intro": 0.8571428571428571,
      "multi-step-word-problems": 0.9090909090909091,
      "unit-conversion": 1,
      "multiply-multi-digit": 0.6296296296296297,
      "volume": 0.4
    }
  }
}
